CyberU/__init__.py
CyberU-2.20.20240318160326.552.dist-info/METADATA
CyberU-2.20.20240318160326.552.dist-info/WHEEL
CyberU-2.20.20240318160326.552.dist-info/top_level.txt
CyberU-2.20.20240318160326.552.dist-info/RECORD
