Metadata-Version: 2.1
Name: CyberU
Version: 2.20.20240318160326.552
Summary: Your spider tool based on selenium and an even general platform based on Python.
Home-page: https://github.com/an-Underpriviliged-ZJUer/Kaleidoscope_public
Author: an-Underpriviliged-ZJUer
Author-email: 1737177378@qq.com
Classifier: License :: OSI Approved :: MIT License
Classifier: Programming Language :: Python :: 3.10
Classifier: Programming Language :: Python :: 3.11
Requires-Dist: numpy
Requires-Dist: retrying
Requires-Dist: requests
Requires-Dist: pywin32
Requires-Dist: winshell
Requires-Dist: setuptools
Requires-Dist: editdistance
Requires-Dist: tenacity
Requires-Dist: lxml
Requires-Dist: playwright
Requires-Dist: moviepy
Requires-Dist: opencv-python
Requires-Dist: pandas
Requires-Dist: dill
Requires-Dist: scikit-image
Requires-Dist: pyperclip
Requires-Dist: selenium
Requires-Dist: webdriver-manager
Requires-Dist: screeninfo
Requires-Dist: keyboard
Requires-Dist: pyautogui
Requires-Dist: pysimplegui
Requires-Dist: win10toast
